mininux_replay_manager/__init__.py
mininux_replay_manager/__main__.py
mininux_replay_manager/controllers.py
mininux_replay_manager/main.py
mininux_replay_manager/main_window.py
mininux_replay_manager/path_dialog.py
mininux_replay_manager/ui/__init__.py
mininux_replay_manager/ui/ui_main_window.py
mininux_replay_manager/ui/ui_path_dialog.py
mininux_replay_manager-0.0.7.dist-info/LICENSE
mininux_replay_manager-0.0.7.dist-info/METADATA
mininux_replay_manager-0.0.7.dist-info/WHEEL
mininux_replay_manager-0.0.7.dist-info/entry_points.txt
mininux_replay_manager-0.0.7.dist-info/top_level.txt
mininux_replay_manager-0.0.7.dist-info/RECORD
