Metadata-Version: 2.1
Name: mininux-replay-manager
Version: 0.0.7
Summary: A simple replay manager made with Python and Qt for the game Project+
Home-page: https://github.com/MininuxDev/mininux-replay-manager
License: UNKNOWN
Platform: UNKNOWN
Classifier: Programming Language :: Python :: 3
Classifier: License :: OSI Approved :: The Unlicense (Unlicense)
Classifier: Operating System :: POSIX
Requires-Python: >=3.6
Requires-Dist: pyside2
